[
  {"name": "Any Inu", "symbol": "AI", "chainId": "solana", "priceUsd": "0.00009713", "marketCap": 97134, "volume24h": 3823.24},
  {"name": "AgentPad", "symbol": "Agent", "chainId": "solana", "priceUsd": "0.00007256", "marketCap": 72491, "volume24h": 59697.96},
  {"name": "Artificial Inu", "symbol": "AI", "chainId": "solana", "priceUsd": "0.0001088", "marketCap": 108822, "volume24h": 7742.54},
  {"name": "The White Whale", "symbol": "AI", "chainId": "solana", "priceUsd": "0.09849", "marketCap": 98491396717, "volume24h": 16.73},
  {"name": "Beast Fan Club", "symbol": "AI", "chainId": "solana", "priceUsd": "0.0003609", "marketCap": 360938007, "volume24h": 1.74},
  {"name": "MOE", "symbol": "AI", "chainId": "solana", "priceUsd": "0.0001509", "marketCap": 14947074, "volume24h": 1050},
  {"name": "The viral rock", "symbol": "AI", "chainId": "solana", "priceUsd": "0.0001609", "marketCap": 160974786, "volume24h": 1047.54},
  {"name": "ai.com", "symbol": "ai", "chainId": "solana", "priceUsd": "0.00002396", "marketCap": 23920, "volume24h": 52724.05},
  {"name": "AI", "symbol": "AI", "chainId": "solana", "priceUsd": "0.000003247", "marketCap": 3247.7, "volume24h": 19375.95},
  {"name": "gensyn", "symbol": "AI", "chainId": "solana", "priceUsd": "0.0003791", "marketCap": 6975817, "volume24h": 0.15},
  {"name": "Any Inu (Wormhole)", "symbol": "AI", "chainId": "solana", "priceUsd": "0.0000008933", "marketCap": 61837, "volume24h": 317.73},
  {"name": "ai.com", "symbol": "AI", "chainId": "solana", "priceUsd": "0.00001741", "marketCap": 17414, "volume24h": 14789.17},
  {"name": "Agents AI", "symbol": "AGENT", "chainId": "solana", "priceUsd": "0.00006340", "marketCap": 63409, "volume24h": 256.66},
  {"name": "Solana Agent", "symbol": "AGENT", "chainId": "solana", "priceUsd": "0.00005492", "marketCap": 54923, "volume24h": 21.8},
  {"name": "AgentAlgo (Wormhole)", "symbol": "AGENT", "chainId": "solana", "priceUsd": "0.009693", "marketCap": 6762, "volume24h": 113.71},
  {"name": "Agent Who Wants A Mac Mini", "symbol": "AGENT", "chainId": "solana", "priceUsd": "0.000003842", "marketCap": 3843, "volume24h": 596.18},
  {"name": "AgentCrypto Fund", "symbol": "AGENT", "chainId": "solana", "priceUsd": "0.000004050", "marketCap": 4050, "volume24h": 282.92},
  {"name": "agentincdotfun", "symbol": "AGENT", "chainId": "solana", "priceUsd": "0.000002334", "marketCap": 2334.12, "volume24h": 1197.12},
  {"name": "Agent Wallet ", "symbol": "Agent", "chainId": "solana", "priceUsd": "0.000002224", "marketCap": 2224.14, "volume24h": 2504.25},
  {"name": "Any Inu", "symbol": "AI", "chainId": "bsc", "priceUsd": "0.0000008811", "marketCap": 103409, "volume24h": 948.93},
  {"name": "Any Inu", "symbol": "AI", "chainId": "bsc", "priceUsd": "0.0000008853", "marketCap": 103866, "volume24h": 2.73},
  {"name": "Artificial Intelligence", "symbol": "AI", "chainId": "bsc", "priceUsd": "0.0003583", "marketCap": 224754, "volume24h": 11.88},
  {"name": "Sleepless AI Token", "symbol": "AI", "chainId": "bsc", "priceUsd": "0.02274", "marketCap": 2957061, "volume24h": 12.98},
  {"name": "Agent Only", "symbol": "AGENT", "chainId": "bsc", "priceUsd": "0.01223", "marketCap": 12235, "volume24h": 2194.93},
  {"name": "Agent Coliseum", "symbol": "Agent", "chainId": "bsc", "priceUsd": "0.000002273", "marketCap": 2273, "volume24h": 6.04},
  {"name": "Agent BNB", "symbol": "Agent", "chainId": "bsc", "priceUsd": "0.000003516", "marketCap": 3516.66, "volume24h": 668.8},
  {"name": "Any Inu", "symbol": "AI", "chainId": "base", "priceUsd": "0.0000008710", "marketCap": 23796, "volume24h": 42.39},
  {"name": "Autistic Intelligence", "symbol": "AI", "chainId": "base", "priceUsd": "0.0000002115", "marketCap": 21153, "volume24h": 1.33},
  {"name": "ai.com", "symbol": "AI", "chainId": "base", "priceUsd": "0.0000002433", "marketCap": 24330, "volume24h": 21.5},
  {"name": "Agentic Wallet", "symbol": "AGENT", "chainId": "base", "priceUsd": "0.0002310", "marketCap": 231070, "volume24h": 904972.44},
  {"name": "Agentic Commerce", "symbol": "AGENT", "chainId": "base", "priceUsd": "0.0000002528", "marketCap": 25285, "volume24h": 0.95},
  {"name": "AgentRobbot", "symbol": "AGENT", "chainId": "base", "priceUsd": "0.0000002509", "marketCap": 25098, "volume24h": 0.95},
  {"name": "charge", "symbol": "Agent", "chainId": "base", "priceUsd": "0.0000002534", "marketCap": 25341, "volume24h": 152.31},
  {"name": "everyagent", "symbol": "agent", "chainId": "base", "priceUsd": "0.0000002575", "marketCap": 25757, "volume24h": 0.96},
  {"name": "AI Agent Builder", "symbol": "AGENT", "chainId": "base", "priceUsd": "0.0000002571", "marketCap": 25716, "volume24h": 0.94},
  {"name": "AiAgent", "symbol": "Agent", "chainId": "base", "priceUsd": "0.0000002549", "marketCap": 25498, "volume24h": 31.58},
  {"name": "Agentic Wallet", "symbol": "AGENT", "chainId": "base", "priceUsd": "0.0000001947", "marketCap": 19475, "volume24h": 16247.88},
  {"name": "Agentic Wallet", "symbol": "AGENT", "chainId": "base", "priceUsd": "0.0000001947", "marketCap": 19472, "volume24h": 30401.37},
  {"name": "Agent_bffaac", "symbol": "AGENT", "chainId": "base", "priceUsd": "0.0000001928", "marketCap": 19287, "volume24h": 0},
  {"name": "everyagent", "symbol": "agent", "chainId": "base", "priceUsd": "0.0000001922", "marketCap": 19222, "volume24h": 0},
  {"name": "Agent_4d1762", "symbol": "AGENT", "chainId": "base", "priceUsd": "0.0000001915", "marketCap": 19158, "volume24h": 0},
  {"name": "Any Inu", "symbol": "AI", "chainId": "ethereum", "priceUsd": "0.0000009100", "marketCap": 225936, "volume24h": 2474.04},
  {"name": "AI PIN", "symbol": "AI", "chainId": "ethereum", "priceUsd": "0.0008292", "marketCap": 82923, "volume24h": 4.84},
  {"name": "AiDoge", "symbol": "AI", "chainId": "ethereum", "priceUsd": "0.0000001145", "marketCap": 114567, "volume24h": 1.13},
  {"name": "AiGrain", "symbol": "AI", "chainId": "ethereum", "priceUsd": "0.0001818", "marketCap": 181818, "volume24h": 906.36},
  {"name": "Any Inu", "symbol": "AI", "chainId": "avalanche", "priceUsd": "0.0000008771", "marketCap": 7671, "volume24h": 247.23},
  {"name": "Flourishing AI Token", "symbol": "AI", "chainId": "polygon", "priceUsd": "0.002798", "marketCap": 66322, "volume24h": 0.01}
]
